display-tools/__init__.py
display-tools/display_image_matrix.py
xptools/__init__.py
xptools/analyze_bubbles.py
xptools/analyze_front.py
xptools/analyze_particles.py
xptools/utils/__init__.py
xptools/utils/imagetools.py
xptools/utils/select_roi.py
xptools/utils/videotools.py
xptools-0.38.post1.data/scripts/analyze_bubbles
xptools-0.38.post1.data/scripts/analyze_front
xptools-0.38.post1.data/scripts/display_image_matrix
xptools-0.38.post1.dist-info/LICENSE
xptools-0.38.post1.dist-info/METADATA
xptools-0.38.post1.dist-info/WHEEL
xptools-0.38.post1.dist-info/top_level.txt
xptools-0.38.post1.dist-info/RECORD
