Metadata-Version: 2.1
Name: xptools
Version: 0.38.post1
Summary: Image and video analysis tools for experimental sciences
Home-page: https://github.com/hlgirard/xptools
Author: Henri-Louis Girard
Author-email: hl.girard@gmail.com
License: MIT
Platform: UNKNOWN
Requires-Dist: opencv-python
Requires-Dist: numpy
Requires-Dist: pandas
Requires-Dist: scikit-image
Requires-Dist: joblib
Requires-Dist: matplotlib
Requires-Dist: av
Requires-Dist: tqdm
